lidar_segmentation.v
// ==========================================
// 1. BUFFER (Registru de Deplasare)
// ==========================================
module window_buffer #(parameter DATA_WIDTH = 16)(
    input wire clk,
    input wire rst_n,
    input wire valid_in,
    input wire [DATA_WIDTH-1:0] data_in,
    output reg [DATA_WIDTH-1:0] p0, p1, p2, p3, p4,
    output reg valid_out
);
    reg [2:0] counter;
    always @(posedge clk or negedge rst_n) begin
        if (!rst_n) begin
            p0 <= 0; p1 <= 0; p2 <= 0; p3 <= 0; p4 <= 0;
            valid_out <= 0; counter <= 0;
        end else if (valid_in) begin
            p4 <= p3; p3 <= p2; p2 <= p1; p1 <= p0; p0 <= data_in;
            if (counter < 5) counter <= counter + 1;
            else valid_out <= 1;
        end
    end
endmodule

// ==========================================
// 2. FILTRU SAVITZKY-GOLAY (Netezire)
// ==========================================
module savitzky_golay_filter #(parameter DATA_WIDTH = 16)(
    input wire clk, rst_n, valid_in,
    input wire signed [DATA_WIDTH-1:0] p0, p1, p2, p3, p4,
    output reg signed [DATA_WIDTH-1:0] filtered_val,
    output reg valid_out
);
    reg signed [DATA_WIDTH+5:0] sum;
    always @(posedge clk or negedge rst_n) begin
        if (!rst_n) begin
            sum <= 0; filtered_val <= 0; valid_out <= 0;
        end else if (valid_in) begin
            sum <= (17 * p2) + (12 * p3) + (12 * p1) - (3 * p4) - (3 * p0);
            filtered_val <= sum >>> 5; 
            valid_out <= 1;
        end else valid_out <= 0;
    end
endmodule

// ==========================================
// 3. LOGICA DE SEGMENTARE (CORECȚIA ESTE AICI)
// ==========================================
// AM SCHIMBAT SLOPE_THRESHOLD DIN 50 IN 8
module segmentation_logic #(parameter DATA_WIDTH = 16, parameter SLOPE_THRESHOLD = 8)(
    input wire clk, rst_n, valid_in,
    input wire signed [DATA_WIDTH-1:0] current_z,
    input wire [DATA_WIDTH-1:0] current_r,
    output reg is_ground,
    output reg valid_out
);
    reg signed [DATA_WIDTH-1:0] prev_z;
    reg [DATA_WIDTH-1:0] prev_r;
    reg [DATA_WIDTH-1:0] delta_z, delta_r;

    always @(posedge clk or negedge rst_n) begin
        if (!rst_n) begin
            prev_z <= 0; prev_r <= 0; is_ground <= 0; valid_out <= 0;
        end else if (valid_in) begin
            prev_z <= current_z;
            prev_r <= current_r;
            
            // Calcul diferență absolută
            delta_z = (current_z > prev_z) ? (current_z - prev_z) : (prev_z - current_z);
            delta_r = (current_r > prev_r) ? (current_r - prev_r) : (prev_r - current_r);
            
            // Verificare pantă cu noul prag (8)
            // Daca diferenta de inaltime e mica fata de distanta, e sol.
            if (delta_z < (delta_r * SLOPE_THRESHOLD)) 
                is_ground <= 1'b1; 
            else 
                is_ground <= 1'b0;
            
            valid_out <= 1'b1;
        end else valid_out <= 0;
    end
endmodule

// ==========================================
// 4. TOP MODULE
// ==========================================
module lidar_ground_segmentation_top #(parameter DATA_WIDTH = 16)(
    input wire clk,
    input wire rst_n,
    input wire data_valid_in,
    input wire [DATA_WIDTH-1:0] raw_z_in,
    input wire [DATA_WIDTH-1:0] raw_r_in,
    output wire segmentation_result,
    output wire result_valid
);
    wire [DATA_WIDTH-1:0] w_p0, w_p1, w_p2, w_p3, w_p4;
    wire buffer_valid, filter_valid;
    wire [DATA_WIDTH-1:0] filtered_z;
    
    window_buffer #(.DATA_WIDTH(DATA_WIDTH)) u_buffer (
        .clk(clk), .rst_n(rst_n), .valid_in(data_valid_in), .data_in(raw_z_in),
        .p0(w_p0), .p1(w_p1), .p2(w_p2), .p3(w_p3), .p4(w_p4),
        .valid_out(buffer_valid)
    );
    
    savitzky_golay_filter #(.DATA_WIDTH(DATA_WIDTH)) u_filter (
        .clk(clk), .rst_n(rst_n), .valid_in(buffer_valid),
        .p0(w_p0), .p1(w_p1), .p2(w_p2), .p3(w_p3), .p4(w_p4),
        .filtered_val(filtered_z),
        .valid_out(filter_valid)
    );
    
    // Observa ca nu mai transmitem parametrul aici, deci el va lua valoarea default (8) din modul
    segmentation_logic #(.DATA_WIDTH(DATA_WIDTH)) u_seg (
        .clk(clk), .rst_n(rst_n), .valid_in(filter_valid),
        .current_z(filtered_z), .current_r(raw_r_in), 
        .is_ground(segmentation_result), .valid_out(result_valid)
    );
endmodule

tb_lidar.v
`timescale 1ns / 1ps

module tb_lidar;

    // ==========================================
    // 1. DEFINIRE SEMNALE ȘI PARAMETRI
    // ==========================================
    parameter DATA_WIDTH = 16;
    
    // Intrări pentru modulul testat (reg)
    reg clk;
    reg rst_n;
    reg data_valid_in;
    reg signed [DATA_WIDTH-1:0] raw_z_in; // 'signed' pentru că filtrul lucrează cu numere cu semn
    reg [DATA_WIDTH-1:0] raw_r_in;
    
    // Ieșiri de la modulul testat (wire)
    wire segmentation_result; // 1 = Sol, 0 = Obstacol
    wire result_valid;
    
    // ==========================================
    // 2. INSTANȚIEREA MODULULUI PRINCIPAL (UUT)
    // ==========================================
    lidar_ground_segmentation_top #(.DATA_WIDTH(DATA_WIDTH)) uut (
        .clk(clk),
        .rst_n(rst_n),
        .data_valid_in(data_valid_in),
        .raw_z_in(raw_z_in),
        .raw_r_in(raw_r_in),
        .segmentation_result(segmentation_result),
        .result_valid(result_valid)
    );
    
    // ==========================================
    // 3. GENERAREA CEASULUI
    // ==========================================
    // Perioada = 10ns (Frecvența = 100 MHz)
    always #5 clk = ~clk;
    
    // ==========================================
    // 4. SCENARIUL DE TEST (STIMULI)
    // ==========================================
    initial begin
        // --- CONFIGURARE PENTRU GTKWAVE ---
        // Aceste linii sunt esențiale pentru a vedea graficele!
        $dumpfile("rezultate.vcd"); 
        $dumpvars(0, tb_lidar);
        
        // --- INIȚIALIZARE ---
        clk = 0;
        rst_n = 0;
        data_valid_in = 0;
        raw_z_in = 0;
        raw_r_in = 0;
        
        $display("--- Start Simulare ---");
        
        // --- RESET ---
        #20 rst_n = 1; // Eliberăm resetul după 20ns
        #10;
        
        // ============================================================
        // TEST CAZ 1: TEREN PLAT (SOL)
        // Înălțimea Z rămâne mică/constantă, Raza R crește.
        // Așteptare: segmentation_result trebuie să fie 1.
        // ============================================================
        $display("Timp: %0t -> Testare SOL PLAT...", $time);
        
        repeat(15) begin
            @(posedge clk);        // Sincronizare cu ceasul
            data_valid_in = 1;
            raw_z_in = 16'd10;     // Înălțime constantă (ex: 10mm)
            raw_r_in = raw_r_in + 10; // Ne îndepărtăm de senzor
        end
        
        // ============================================================
        // TEST CAZ 2: OBSTACOL BRUSC (ZID/BORDURĂ)
        // Înălțimea Z sare brusc la o valoare mare.
        // Așteptare: segmentation_result trebuie să devină 0.
        // ============================================================
        $display("Timp: %0t -> Testare OBSTACOL...", $time);
        
        repeat(10) begin
            @(posedge clk);
            data_valid_in = 1;
            raw_z_in = 16'd200;    // Săritură la 200mm (obstacol)
            raw_r_in = raw_r_in + 10;
        end
        
        // ============================================================
        // TEST CAZ 3: REVENIRE PE SOL
        // Înălțimea Z revine la valoarea mică.
        // Așteptare: segmentation_result revine la 1.
        // ============================================================
        $display("Timp: %0t -> Revenire la SOL...", $time);
        
        repeat(15) begin
            @(posedge clk);
            data_valid_in = 1;
            raw_z_in = 16'd10;     // Din nou jos
            raw_r_in = raw_r_in + 10;
        end

        // Oprim datele valide
        @(posedge clk);
        data_valid_in = 0;
        
        // Mai lăsăm simularea să curgă puțin pentru a vedea ultimele rezultate
        #50;
        
        $display("--- Final Simulare ---");
        $finish; // Oprește simularea
    end
    
endmodule

rezultate.vcd
$date
	Fri Dec 19 17:04:26 2025
$end
$version
	Icarus Verilog
$end
$timescale
	1ps
$end
$scope module tb_lidar $end
$var wire 1 ! segmentation_result $end
$var wire 1 " result_valid $end
$var parameter 32 # DATA_WIDTH $end
$var reg 1 $ clk $end
$var reg 1 % data_valid_in $end
$var reg 16 & raw_r_in [15:0] $end
$var reg 16 ' raw_z_in [15:0] $end
$var reg 1 ( rst_n $end
$scope module uut $end
$var wire 1 $ clk $end
$var wire 1 % data_valid_in $end
$var wire 16 ) raw_r_in [15:0] $end
$var wire 16 * raw_z_in [15:0] $end
$var wire 1 ( rst_n $end
$var wire 16 + w_p4 [15:0] $end
$var wire 16 , w_p3 [15:0] $end
$var wire 16 - w_p2 [15:0] $end
$var wire 16 . w_p1 [15:0] $end
$var wire 16 / w_p0 [15:0] $end
$var wire 1 ! segmentation_result $end
$var wire 1 " result_valid $end
$var wire 16 0 filtered_z [15:0] $end
$var wire 1 1 filter_valid $end
$var wire 1 2 buffer_valid $end
$var parameter 32 3 DATA_WIDTH $end
$scope module u_buffer $end
$var wire 1 $ clk $end
$var wire 16 4 data_in [15:0] $end
$var wire 1 ( rst_n $end
$var wire 1 % valid_in $end
$var parameter 32 5 DATA_WIDTH $end
$var reg 3 6 counter [2:0] $end
$var reg 16 7 p0 [15:0] $end
$var reg 16 8 p1 [15:0] $end
$var reg 16 9 p2 [15:0] $end
$var reg 16 : p3 [15:0] $end
$var reg 16 ; p4 [15:0] $end
$var reg 1 2 valid_out $end
$upscope $end
$scope module u_filter $end
$var wire 1 $ clk $end
$var wire 16 < p0 [15:0] $end
$var wire 16 = p1 [15:0] $end
$var wire 16 > p2 [15:0] $end
$var wire 16 ? p3 [15:0] $end
$var wire 16 @ p4 [15:0] $end
$var wire 1 ( rst_n $end
$var wire 1 2 valid_in $end
$var parameter 32 A DATA_WIDTH $end
$var reg 16 B filtered_val [15:0] $end
$var reg 22 C sum [21:0] $end
$var reg 1 1 valid_out $end
$upscope $end
$scope module u_seg $end
$var wire 1 $ clk $end
$var wire 16 D current_r [15:0] $end
$var wire 16 E current_z [15:0] $end
$var wire 1 ( rst_n $end
$var wire 1 1 valid_in $end
$var parameter 32 F DATA_WIDTH $end
$var parameter 32 G SLOPE_THRESHOLD $end
$var reg 16 H delta_r [15:0] $end
$var reg 16 I delta_z [15:0] $end
$var reg 1 ! is_ground $end
$var reg 16 J prev_r [15:0] $end
$var reg 16 K prev_z [15:0] $end
$var reg 1 " valid_out $end
$upscope $end
$upscope $end
$upscope $end
$enddefinitions $end
$comment Show the parameter values. $end
$dumpall
b1000 G
b10000 F
b10000 A
b10000 5
b10000 3
b10000 #
$end
#0
$dumpvars
b0 K
b0 J
bx I
bx H
b0 E
b0 D
b0 C
b0 B
b0 @
b0 ?
b0 >
b0 =
b0 <
b0 ;
b0 :
b0 9
b0 8
b0 7
b0 6
b0 4
02
01
b0 0
b0 /
b0 .
b0 -
b0 ,
b0 +
b0 *
b0 )
0(
b0 '
b0 &
0%
0$
0"
0!
$end
#5000
1$
#10000
0$
#15000
1$
#20000
0$
1(
#25000
1$
#30000
0$
#35000
b1 6
b1010 /
b1010 7
b1010 <
b1010 &
b1010 )
b1010 D
b1010 '
b1010 *
b1010 4
1%
1$
#40000
0$
#45000
b10 6
b1010 .
b1010 8
b1010 =
b10100 &
b10100 )
b10100 D
1$
#50000
0$
#55000
b11 6
b1010 -
b1010 9
b1010 >
b11110 &
b11110 )
b11110 D
1$
#60000
0$
#65000
b100 6
b1010 ,
b1010 :
b1010 ?
b101000 &
b101000 )
b101000 D
1$
#70000
0$
#75000
b101 6
b1010 +
b1010 ;
b1010 @
b110010 &
b110010 )
b110010 D
1$
#80000
0$
#85000
12
b111100 &
b111100 )
b111100 D
1$
#90000
0$
#95000
11
b101011110 C
b1000110 &
b1000110 )
b1000110 D
1$
#100000
0$
#105000
1"
1!
b1010000 J
b1010 0
b1010 B
b1010 E
b1010000 H
b0 I
b1010000 &
b1010000 )
b1010000 D
1$
#110000
0$
#115000
b1011010 J
b1010 K
b1010 H
b1010 I
b1011010 &
b1011010 )
b1011010 D
1$
#120000
0$
#125000
b1100100 J
b0 I
b1100100 &
b1100100 )
b1100100 D
1$
#130000
0$
#135000
b1101110 J
b1101110 &
b1101110 )
b1101110 D
1$
#140000
0$
#145000
b1111000 J
b1111000 &
b1111000 )
b1111000 D
1$
#150000
0$
#155000
b10000010 J
b10000010 &
b10000010 )
b10000010 D
1$
#160000
0$
#165000
b10001100 J
b10001100 &
b10001100 )
b10001100 D
1$
#170000
0$
#175000
b10010110 J
b10010110 &
b10010110 )
b10010110 D
1$
#180000
0$
#185000
b10100000 J
b11001000 /
b11001000 7
b11001000 <
b10100000 &
b10100000 )
b10100000 D
b11001000 '
b11001000 *
b11001000 4
1$
#190000
0$
#195000
b11001000 .
b11001000 8
b11001000 =
b1111111111111100100100 C
b10101010 J
b10101010 &
b10101010 )
b10101010 D
1$
#200000
0$
#205000
b10110100 J
b1111111111111001 0
b1111111111111001 B
b1111111111111001 E
b100000001100 C
b11001000 -
b11001000 9
b11001000 >
b10110100 &
b10110100 )
b10110100 D
1$
#210000
0$
#215000
b11001000 ,
b11001000 :
b11001000 ?
b1000000 0
b1000000 B
b1000000 E
b1010010101010 C
b10111110 J
b1111111111111001 K
b10001 I
b10111110 &
b10111110 )
b10111110 D
1$
#220000
0$
#225000
b11001000 J
b1000000 K
b10100101 0
b10100101 B
b10100101 E
b1110110010010 C
b11001000 +
b11001000 ;
b11001000 @
b1000111 I
b11001000 &
b11001000 )
b11001000 D
1$
#230000
0$
#235000
b11101100 0
b11101100 B
b11101100 E
b1101101011000 C
0!
b11010010 J
b10100101 K
b1100101 I
b11010010 &
b11010010 )
b11010010 D
1$
#240000
0$
#245000
1!
b11011100 J
b11101100 K
b11011010 0
b11011010 B
b11011010 E
b1000111 I
b11011100 &
b11011100 )
b11011100 D
1$
#250000
0$
#255000
b11100110 J
b11011010 K
b10010 I
b11100110 &
b11100110 )
b11100110 D
1$
#260000
0$
#265000
b11110000 J
b0 I
b11110000 &
b11110000 )
b11110000 D
1$
#270000
0$
#275000
b11111010 J
b11111010 &
b11111010 )
b11111010 D
1$
#280000
0$
#285000
b100000100 J
b1010 /
b1010 7
b1010 <
b100000100 &
b100000100 )
b100000100 D
b1010 '
b1010 *
b1010 4
1$
#290000
0$
#295000
b1010 .
b1010 8
b1010 =
b1110110010010 C
b100001110 J
b100001110 &
b100001110 )
b100001110 D
1$
#300000
0$
#305000
b100011000 J
b11101100 0
b11101100 B
b11101100 E
b1010010101010 C
b1010 -
b1010 9
b1010 >
b100011000 &
b100011000 )
b100011000 D
1$
#310000
0$
#315000
b1010 ,
b1010 :
b1010 ?
b10100101 0
b10100101 B
b10100101 E
b100000001100 C
b100100010 J
b11101100 K
b10010 I
b100100010 &
b100100010 )
b100100010 D
1$
#320000
0$
#325000
b100101100 J
b10100101 K
b1000000 0
b1000000 B
b1000000 E
b1111111111111100100100 C
b1010 +
b1010 ;
b1010 @
b1000111 I
b100101100 &
b100101100 )
b100101100 D
1$
#330000
0$
#335000
b1111111111111001 0
b1111111111111001 B
b1111111111111001 E
b101011110 C
0!
b100110110 J
b1000000 K
b1100101 I
b100110110 &
b100110110 )
b100110110 D
1$
#340000
0$
#345000
1!
b101000000 J
b1111111111111001 K
b1010 0
b1010 B
b1010 E
b1000111 I
b101000000 &
b101000000 )
b101000000 D
1$
#350000
0$
#355000
b101001010 J
b1010 K
b10001 I
b101001010 &
b101001010 )
b101001010 D
1$
#360000
0$
#365000
b101010100 J
b0 I
b101010100 &
b101010100 )
b101010100 D
1$
#370000
0$
#375000
b101011110 J
b101011110 &
b101011110 )
b101011110 D
1$
#380000
0$
#385000
b101101000 J
b101101000 &
b101101000 )
b101101000 D
1$
#390000
0$
#395000
b101110010 J
b101110010 &
b101110010 )
b101110010 D
1$
#400000
0$
#405000
b101111100 J
b101111100 &
b101111100 )
b101111100 D
1$
#410000
0$
#415000
b110000110 J
b110000110 &
b110000110 )
b110000110 D
1$
#420000
0$
#425000
b110010000 J
b110010000 &
b110010000 )
b110010000 D
1$
#430000
0$
#435000
0!
b0 H
0%
1$
